demoben/__init__.py
demoben/demoben.py
demoben-0.1.5.dist-info/WHEEL
demoben-0.1.5.dist-info/METADATA
demoben-0.1.5.dist-info/RECORD
